smlep_news/__init__.py
smlep_news/sender.py
smlep_news/tools.py
smlep_news/exchangerates/__init__.py
smlep_news/exchangerates/rates.py
smlep_news/figaro/__init__.py
smlep_news/figaro/fig_article.py
smlep_news/github/__init__.py
smlep_news/github/repository.py
smlep_news/guardian/__init__.py
smlep_news/guardian/article.py
smlep_news/hackernews/__init__.py
smlep_news/mail/__init__.py
smlep_news/mail/format.py
smlep_news/medium/__init__.py
smlep_news/medium/topics.json
smlep_news/nytimes/__init__.py
smlep_news/nytimes/article.py
smlep_news/product_hunt/__init__.py
smlep_news/product_hunt/product.py
smlep_news/runner/__init__.py
smlep_news/weather/__init__.py
smlep_news/weather/weather.py
smlep_news-0.3.1.dist-info/LICENSE
smlep_news-0.3.1.dist-info/METADATA
smlep_news-0.3.1.dist-info/WHEEL
smlep_news-0.3.1.dist-info/top_level.txt
smlep_news-0.3.1.dist-info/RECORD
