Metadata-Version: 2.1
Name: smlep-news
Version: 0.3.1
Summary: Custom news scrapper
Home-page: UNKNOWN
License: UNKNOWN
Platform: UNKNOWN
Classifier: Programming Language :: Python :: 3
Classifier: License :: OSI Approved :: MIT License
Classifier: Operating System :: OS Independent
Requires-Python: >=3.7
Requires-Dist: beautifulsoup4 (==4.9.3)
Requires-Dist: feedparser (==6.0.2)
Requires-Dist: requests (==2.25.1)
